{
  "omni_id": "OMNI-019355006",
  "composition": {
    "target": "kidney",
    "action": "repair",
    "means": "contrast dye enhanced X-ray"
  },
  "plain_language": {
    "en": "Anatomical reconstruction of the kidney with infusion of contrast fluid and X-ray mapping",
    "es": "Reconstrucción anatómica de riñón con infusión de líquido de contraste y radiografías",
    "fr": "Reconstruction anatomique de rein avec injection de produit de contraste et radiographie",
    "ar": "إعادة بناء تشريحية لـ الكلية مع حقن صبغة التباين والأشعة السينية",
    "hi": "कंट्रास्ट डाई और एक्स-रे मैपिंग के साथ गुर्दा (किडनी) का शारीरिक पुनर्निर्माण (मरम्मत)",
    "zh": "配合造影剂灌注及X光造影结构修补与重建肾脏",
    "pt": "Reconstrução anatômica de rim com infusão de contraste e radiografia"
  },
  "crosswalks": {
    "cpt": "85006",
    "ichi": "KID.RE.CO",
    "snomed_ct": "940055006",
    "icd11_pcs": "KRC1.0",
    "icd10_cm": "0KB006Z"
  },
  "notes": "Programmatically generated post-coordinated expansion code.",
  "provisional": true,
  "version": "0.2.0",
  "added": "2026-05"
}