{
  "omni_id": "OMNI-014839924",
  "composition": {
    "target": "kidney",
    "action": "imaging",
    "means": "open"
  },
  "plain_language": {
    "en": "Diagnostic imaging scan of the kidney through an open incision",
    "es": "Escaneo de diagnóstico por imágenes de riñón a través de una incisión abierta",
    "fr": "Scanner d'imagerie diagnostique de rein par incision ouverte",
    "ar": "تصوير تشخيصي لـ الكلية عبر شق جراحي مفتوح",
    "hi": "खुली सर्जरी द्वारा गुर्दा (किडनी) का डायग्नोस्टिक इमेजिंग स्कैन",
    "zh": "通过开放性切口进行诊断影像学扫描肾脏",
    "pt": "Exame de imagem diagnóstica de rim através de incisão aberta"
  },
  "crosswalks": {
    "cpt": "89924",
    "ichi": "KID.IM.OP",
    "snomed_ct": "940039924",
    "icd11_pcs": "KIO1.0",
    "icd10_cm": "0KB924Z"
  },
  "notes": "Programmatically generated post-coordinated expansion code.",
  "provisional": true,
  "version": "0.2.0",
  "added": "2026-05"
}